README.rst
setup.cfg
setup.py
cozydb/__init__.py
cozydb/cozydb.py
cozydb.egg-info/PKG-INFO
cozydb.egg-info/SOURCES.txt
cozydb.egg-info/dependency_links.txt
cozydb.egg-info/entry_points.txt
cozydb.egg-info/not-zip-safe
cozydb.egg-info/requires.txt
cozydb.egg-info/top_level.txt