Metadata-Version: 1.1
Name: cozydb
Version: 0.1.7
Summary: cozydb is a cozy MySQL-python wrapper
Home-page: https://github.com/xupeng/cozydb
Author: Xupeng Yun
Author-email: recordus@gmail.com
License: BSD
Platform: UNKNOWN
Classifier: Environment :: Other Environment
Classifier: License :: OSI Approved :: BSD License
Classifier: Operating System :: MacOS :: MacOS X
Classifier: Operating System :: Microsoft :: Windows :: Windows NT/2000
Classifier: Operating System :: OS Independent
Classifier: Operating System :: POSIX
Classifier: Operating System :: POSIX :: Linux
Classifier: Operating System :: Unix
Classifier: Programming Language :: Python
Classifier: Topic :: Database
Classifier: Topic :: Database :: Database Engines/Servers
